[{"District":"Jamalpur","Thana":"Dewangonj","SubOffice":"Dewangonj","Post Code":2030},
{"District":"Jamalpur","Thana":"Dewangonj","SubOffice":"Dewangonj S. Mills","Post Code":2031},
{"District":"Jamalpur","Thana":"Islampur","SubOffice":"Durmoot","Post Code":2021},
{"District":"Jamalpur","Thana":"Islampur","SubOffice":"Gilabari","Post Code":2022},
{"District":"Jamalpur","Thana":"Islampur","SubOffice":"Islampur","Post Code":2020},
{"District":"Jamalpur","Thana":"Jamalpur","SubOffice":"Jamalpur","Post Code":2000},
{"District":"Jamalpur","Thana":"Jamalpur","SubOffice":"Nandina","Post Code":2001},
{"District":"Jamalpur","Thana":"Jamalpur","SubOffice":"Narundi","Post Code":2002},
{"District":"Jamalpur","Thana":"Malandah","SubOffice":"Jamalpur","Post Code":2011},
{"District":"Jamalpur","Thana":"Malandah","SubOffice":"Mahmoodpur","Post Code":2013},
{"District":"Jamalpur","Thana":"Malandah","SubOffice":"Malancha","Post Code":2012},
{"District":"Jamalpur","Thana":"Malandah","SubOffice":"Malandah","Post Code":2010},
{"District":"Jamalpur","Thana":"Mathargonj","SubOffice":"Balijhuri","Post Code":2041},
{"District":"Jamalpur","Thana":"Mathargonj","SubOffice":"Mathargonj","Post Code":2040},
{"District":"Jamalpur","Thana":"Shorishabari","SubOffice":"Bausee","Post Code":2052},
{"District":"Jamalpur","Thana":"Shorishabari","SubOffice":"Gunerbari","Post Code":2051},
{"District":"Jamalpur","Thana":"Shorishabari","SubOffice":"Jagannath Ghat","Post Code":2053},
{"District":"Jamalpur","Thana":"Shorishabari","SubOffice":"Jamuna Sar Karkhana","Post Code":2055},
{"District":"Jamalpur","Thana":"Shorishabari","SubOffice":"Pingna","Post Code":2054},
{"District":"Jamalpur","Thana":"Shorishabari","SubOffice":"Shorishabari","Post Code":2050},
{"District":"Mymensingh","Thana":"Bhaluka","SubOffice":"Bhaluka","Post Code":2240},
{"District":"Mymensingh","Thana":"Fulbaria","SubOffice":"Fulbaria","Post Code":2216},
{"District":"Mymensingh","Thana":"Gaforgaon","SubOffice":"Duttarbazar","Post Code":2234},
{"District":"Mymensingh","Thana":"Gaforgaon","SubOffice":"Gaforgaon","Post Code":2230},
{"District":"Mymensingh","Thana":"Gaforgaon","SubOffice":"Kandipara","Post Code":2233},
{"District":"Mymensingh","Thana":"Gaforgaon","SubOffice":"Shibganj","Post Code":2231},
{"District":"Mymensingh","Thana":"Gaforgaon","SubOffice":"Usti","Post Code":2232},
{"District":"Mymensingh","Thana":"Gouripur","SubOffice":"Gouripur","Post Code":2270},
{"District":"Mymensingh","Thana":"Gouripur","SubOffice":"Ramgopalpur","Post Code":2271},
{"District":"Mymensingh","Thana":"Haluaghat","SubOffice":"Dhara","Post Code":2261},
{"District":"Mymensingh","Thana":"Haluaghat","SubOffice":"Haluaghat","Post Code":2260},
{"District":"Mymensingh","Thana":"Haluaghat","SubOffice":"Munshirhat","Post Code":2262},
{"District":"Mymensingh","Thana":"Isshwargonj","SubOffice":"Atharabari","Post Code":2282},
{"District":"Mymensingh","Thana":"Isshwargonj","SubOffice":"Isshwargonj","Post Code":2280},
{"District":"Mymensingh","Thana":"Isshwargonj","SubOffice":"Sohagi","Post Code":2281},
{"District":"Mymensingh","Thana":"Muktagachha","SubOffice":"Muktagachha","Post Code":2210},
{"District":"Mymensingh","Thana":"Mymensingh Sadar","SubOffice":"Agriculture Universi","Post Code":2202},
{"District":"Mymensingh","Thana":"Mymensingh Sadar","SubOffice":"Biddyaganj","Post Code":2204},
{"District":"Mymensingh","Thana":"Mymensingh Sadar","SubOffice":"Kawatkhali","Post Code":2201},
{"District":"Mymensingh","Thana":"Mymensingh Sadar","SubOffice":"Mymensingh Sadar","Post Code":2200},
{"District":"Mymensingh","Thana":"Mymensingh Sadar","SubOffice":"Pearpur","Post Code":2205},
{"District":"Mymensingh","Thana":"Mymensingh Sadar","SubOffice":"Shombhuganj","Post Code":2203},
{"District":"Mymensingh","Thana":"Nandail","SubOffice":"Gangail","Post Code":2291},
{"District":"Mymensingh","Thana":"Nandail","SubOffice":"Nandail","Post Code":2290},
{"District":"Mymensingh","Thana":"Phulpur","SubOffice":"Beltia","Post Code":2251},
{"District":"Mymensingh","Thana":"Phulpur","SubOffice":"Phulpur","Post Code":2250},
{"District":"Mymensingh","Thana":"Phulpur","SubOffice":"Tarakanda","Post Code":2252},
{"District":"Mymensingh","Thana":"Trishal","SubOffice":"Ahmadbad","Post Code":2221},
{"District":"Mymensingh","Thana":"Trishal","SubOffice":"Dhala","Post Code":2223},
{"District":"Mymensingh","Thana":"Trishal","SubOffice":"Ram Amritaganj","Post Code":2222},
{"District":"Mymensingh","Thana":"Trishal","SubOffice":"Trishal","Post Code":2220},
{"District":"Netrakona","Thana":"Susung Durgapur","SubOffice":"Susnng Durgapur","Post Code":2420},
{"District":"Netrakona","Thana":"Atpara","SubOffice":"Atpara","Post Code":2470},
{"District":"Netrakona","Thana":"Barhatta","SubOffice":"Barhatta","Post Code":2440},
{"District":"Netrakona","Thana":"Dharmapasha","SubOffice":"Dharampasha","Post Code":2450},
{"District":"Netrakona","Thana":"Dhobaura","SubOffice":"Dhobaura","Post Code":2416},
{"District":"Netrakona","Thana":"Dhobaura","SubOffice":"Sakoai","Post Code":2417},
{"District":"Netrakona","Thana":"Kalmakanda","SubOffice":"Kalmakanda","Post Code":2430},
{"District":"Netrakona","Thana":"Kendua","SubOffice":"Kendua","Post Code":2480},
{"District":"Netrakona","Thana":"Khaliajuri","SubOffice":"Khaliajhri","Post Code":2460},
{"District":"Netrakona","Thana":"Khaliajuri","SubOffice":"Shaldigha","Post Code":2462},
{"District":"Netrakona","Thana":"Madan","SubOffice":"Madan","Post Code":2490},
{"District":"Netrakona","Thana":"Moddhynagar","SubOffice":"Moddoynagar","Post Code":2456},
{"District":"Netrakona","Thana":"Mohanganj","SubOffice":"Mohanganj","Post Code":2446},
{"District":"Netrakona","Thana":"Netrakona Sadar","SubOffice":"Baikherhati","Post Code":2401},
{"District":"Netrakona","Thana":"Netrakona Sadar","SubOffice":"Netrakona Sadar","Post Code":2400},
{"District":"Netrakona","Thana":"Purbadhola","SubOffice":"Jaria Jhanjhail","Post Code":2412},
{"District":"Netrakona","Thana":"Purbadhola","SubOffice":"Purbadhola","Post Code":2410},
{"District":"Netrakona","Thana":"Purbadhola","SubOffice":"Shamgonj","Post Code":2411},
{"District":"Sherpur","Thana":"Bakshigonj","SubOffice":"Bakshigonj","Post Code":2140},
{"District":"Sherpur","Thana":"Jhinaigati","SubOffice":"Jhinaigati","Post Code":2120},
{"District":"Sherpur","Thana":"Nakla","SubOffice":"Gonopaddi","Post Code":2151},
{"District":"Sherpur","Thana":"Nakla","SubOffice":"Nakla","Post Code":2150},
{"District":"Sherpur","Thana":"Nalitabari","SubOffice":"Hatibandha","Post Code":2111},
{"District":"Sherpur","Thana":"Nalitabari","SubOffice":"Nalitabari","Post Code":2110},
{"District":"Sherpur","Thana":"Sherpur Shadar","SubOffice":"Sherpur Shadar","Post Code":2100},
{"District":"Sherpur","Thana":"Shribardi","SubOffice":"Shribardi","Post Code":2130}]
